concordance/__init__.py
concordance/concordance.py
concordance/main.py
concordance/normalize.py
concordance-0.1.3.dist-info/METADATA
concordance-0.1.3.dist-info/WHEEL
concordance-0.1.3.dist-info/top_level.txt
concordance-0.1.3.dist-info/RECORD
