Metadata-Version: 2.1
Name: concordance
Version: 0.1.3
Summary: Dilbilimcilerin ihtiyaçları doğrultusunda geliştirilen concordance aracı
Home-page: UNKNOWN
Author: İlker Atagün
Author-email: <ilker.atagun@gmail.com>
License: UNKNOWN
Keywords: python,nlp,linguistics,concordance
Platform: UNKNOWN
Classifier: Development Status :: 1 - Planning
Classifier: Intended Audience :: Developers
Classifier: Programming Language :: Python :: 3
Classifier: Operating System :: Microsoft :: Windows
Requires-Dist: click (==7.1.2)
Requires-Dist: joblib (==1.0.1)
Requires-Dist: nltk (==3.5)
Requires-Dist: pandas
Requires-Dist: regex (==2020.11.13)
Requires-Dist: tqdm (==4.59.0)
